LICENSE
MANIFEST.in
README.rst
setup.cfg
setup.py
docs/Makefile
docs/api.rst
docs/conf.py
docs/config.rst
docs/contributing.rst
docs/deploy.rst
docs/index.rst
docs/install.rst
docs/news.rst
docs/overview.rst
docs/requirements.txt
integration_tests/__init__.py
integration_tests/test_webservice.py
integration_tests/test_website.py
samge_fork_scrapyd.egg-info/PKG-INFO
samge_fork_scrapyd.egg-info/SOURCES.txt
samge_fork_scrapyd.egg-info/dependency_links.txt
samge_fork_scrapyd.egg-info/entry_points.txt
samge_fork_scrapyd.egg-info/not-zip-safe
samge_fork_scrapyd.egg-info/requires.txt
samge_fork_scrapyd.egg-info/top_level.txt
scrapyd/VERSION
scrapyd/__init__.py
scrapyd/_deprecate.py
scrapyd/app.py
scrapyd/basicauth.py
scrapyd/config.py
scrapyd/default_scrapyd.conf
scrapyd/eggstorage.py
scrapyd/eggutils.py
scrapyd/environ.py
scrapyd/interfaces.py
scrapyd/jobstorage.py
scrapyd/launcher.py
scrapyd/poller.py
scrapyd/runner.py
scrapyd/scheduler.py
scrapyd/spiderqueue.py
scrapyd/sqlite.py
scrapyd/txapp.py
scrapyd/utils.py
scrapyd/webservice.py
scrapyd/website.py
scrapyd/scripts/__init__.py
scrapyd/scripts/scrapyd_run.py
scrapyd/tests/__init__.py
scrapyd/tests/conftest.py
scrapyd/tests/logstdout.egg
scrapyd/tests/mockserver.py
scrapyd/tests/mybot.egg
scrapyd/tests/mybot2.egg
scrapyd/tests/mybot3.egg
scrapyd/tests/mybotunicode.egg
scrapyd/tests/quotesbot.egg
scrapyd/tests/quotesbot_asyncio.egg
scrapyd/tests/start_mock_app.py
scrapyd/tests/test_dont_load_settings.py
scrapyd/tests/test_eggstorage.py
scrapyd/tests/test_endpoints.py
scrapyd/tests/test_environ.py
scrapyd/tests/test_jobstorage.py
scrapyd/tests/test_poller.py
scrapyd/tests/test_scheduler.py
scrapyd/tests/test_scripts.py
scrapyd/tests/test_spiderqueue.py
scrapyd/tests/test_sqlite.py
scrapyd/tests/test_utils.py
scrapyd/tests/test_webservice.py
scrapyd/tests/test_website.py